warfle/__init__.py
warfle/main.py
warfle/cli/__init__.py
warfle/cli/commands.py
warfle/cli/utils.py
warfle/cli/texts/config-update-success.warfle
warfle/cli/texts/init.warfle
warfle/cli/texts/no-key.warfle
warfle/cli/texts/no-warfle.warfle
warfle/compiler/__init__.py
warfle/compiler/compile.py
warfle_deploy_cli-1.0.0.dist-info/LICENSE.md
warfle_deploy_cli-1.0.0.dist-info/METADATA
warfle_deploy_cli-1.0.0.dist-info/WHEEL
warfle_deploy_cli-1.0.0.dist-info/entry_points.txt
warfle_deploy_cli-1.0.0.dist-info/top_level.txt
warfle_deploy_cli-1.0.0.dist-info/RECORD
