Metadata-Version: 2.1
Name: warfle-deploy-cli
Version: 1.0.0
Summary: Easy to use command line deployer for smart contracts.
Home-page: https://www.github.com/egesabanci/warfle
Author: Ege Sabanci
Author-email: egesabanci@outlook.com.tr
License: MIT
Platform: UNKNOWN
Classifier: License :: OSI Approved :: MIT License
Classifier: Programming Language :: Python :: 3
Classifier: Programming Language :: Python :: 3.8
Requires-Dist: Pygments (==2.11.2)
Requires-Dist: SecretStorage (==3.3.1)
Requires-Dist: aiohttp (==3.8.1)
Requires-Dist: aiosignal (==1.2.0)
Requires-Dist: async-timeout (==4.0.2)
Requires-Dist: attrs (==21.4.0)
Requires-Dist: base58 (==2.1.1)
Requires-Dist: bitarray (==1.2.2)
Requires-Dist: bleach (==4.1.0)
Requires-Dist: certifi (==2021.10.8)
Requires-Dist: cffi (==1.15.0)
Requires-Dist: charset-normalizer (==2.0.12)
Requires-Dist: colorama (==0.4.4)
Requires-Dist: cryptography (==36.0.2)
Requires-Dist: cytoolz (==0.11.2)
Requires-Dist: docutils (==0.18.1)
Requires-Dist: eth-abi (==2.1.1)
Requires-Dist: eth-account (==0.5.7)
Requires-Dist: eth-hash (==0.3.2)
Requires-Dist: eth-keyfile (==0.5.1)
Requires-Dist: eth-keys (==0.3.4)
Requires-Dist: eth-rlp (==0.3.0)
Requires-Dist: eth-typing (==2.3.0)
Requires-Dist: eth-utils (==1.10.0)
Requires-Dist: fire (==0.4.0)
Requires-Dist: frozenlist (==1.3.0)
Requires-Dist: hexbytes (==0.2.2)
Requires-Dist: idna (==3.3)
Requires-Dist: importlib-metadata (==4.11.3)
Requires-Dist: ipfshttpclient (==0.8.0a2)
Requires-Dist: jeepney (==0.7.1)
Requires-Dist: jsonschema (==3.2.0)
Requires-Dist: keyring (==23.5.0)
Requires-Dist: lru-dict (==1.1.7)
Requires-Dist: multiaddr (==0.0.9)
Requires-Dist: multidict (==6.0.2)
Requires-Dist: netaddr (==0.8.0)
Requires-Dist: packaging (==21.3)
Requires-Dist: parsimonious (==0.8.1)
Requires-Dist: pkginfo (==1.8.2)
Requires-Dist: protobuf (==3.19.4)
Requires-Dist: py-solc-x (==1.1.1)
Requires-Dist: pycparser (==2.21)
Requires-Dist: pycryptodome (==3.14.1)
Requires-Dist: pyparsing (==3.0.7)
Requires-Dist: pyrsistent (==0.18.1)
Requires-Dist: readme-renderer (==34.0)
Requires-Dist: requests-toolbelt (==0.9.1)
Requires-Dist: requests (==2.27.1)
Requires-Dist: rfc3986 (==2.0.0)
Requires-Dist: rlp (==2.0.1)
Requires-Dist: semantic-version (==2.9.0)
Requires-Dist: six (==1.16.0)
Requires-Dist: termcolor (==1.1.0)
Requires-Dist: toolz (==0.11.2)
Requires-Dist: tqdm (==4.63.0)
Requires-Dist: twine (==3.8.0)
Requires-Dist: urllib3 (==1.26.9)
Requires-Dist: varint (==1.0.2)
Requires-Dist: web3 (==5.28.0)
Requires-Dist: webencodings (==0.5.1)
Requires-Dist: websockets (==9.1)
Requires-Dist: yarl (==1.7.2)
Requires-Dist: zipp (==3.7.0)
